Metadata-Version: 1.0
Name: BestSignAPI
Version: 1.1.0
Summary: Python library for BestSign API
Home-page: https://www.bestsign.cn
Author: BestSign Test Team
Author-email: allqa@bestsign.cn
License: Apache License, Version 2.0
Keywords: robot auto automation API
Platform: UNKNOWN
